letsagree/__init__.py
letsagree/admin.py
letsagree/apps.py
letsagree/forms.py
letsagree/helpers.py
letsagree/middleware.py
letsagree/models.py
letsagree/querysets.py
letsagree/urls.py
letsagree/views.py
letsagree/migrations/__init__.py
letsagree/static/letsagree/letsagree.css
letsagree/templates/letsagree/pending.html
test_setup/__init__.py
test_setup/i18n_settings.py
test_setup/settings.py
test_setup/urls.py
django_letsagree-1.1.9.dist-info/LICENSE
django_letsagree-1.1.9.dist-info/METADATA
django_letsagree-1.1.9.dist-info/WHEEL
django_letsagree-1.1.9.dist-info/top_level.txt
django_letsagree-1.1.9.dist-info/RECORD
